clickhouse_balanced/__init__.py
clickhouse_balanced/client.py
clickhouse_balanced_talenttech_oss-0.0.1.dist-info/LICENSE.txt
clickhouse_balanced_talenttech_oss-0.0.1.dist-info/METADATA
clickhouse_balanced_talenttech_oss-0.0.1.dist-info/WHEEL
clickhouse_balanced_talenttech_oss-0.0.1.dist-info/top_level.txt
clickhouse_balanced_talenttech_oss-0.0.1.dist-info/RECORD
