Metadata-Version: 2.1
Name: clickhouse-balanced-talenttech-oss
Version: 0.0.1
Summary: Balanced ClickHouse Client
Home-page: https://github.com/severgroup-tt/topmind-commons
Author: Pavel Popov
Author-email: p.popov@talenttech.ru
License: MIT
Platform: UNKNOWN
Classifier: Programming Language :: Python :: 3
Classifier: License :: OSI Approved :: MIT License
Classifier: Operating System :: OS Independent
Requires-Python: >=3.6
Requires-Dist: clickhouse-driver
